[
  {
    "_id": { "$oid": "5c3b64fb547a852e622831e9" },
    "assistCount": 5522,
    "banCount": 105,
    "deathCount": 4787,
    "gameTime": { "$numberLong": "914125" },
    "key": 1,
    "killCount": 3701,
    "lossCount": 456,
    "magicDmg": { "$numberLong": "9679470" },
    "physDmg": { "$numberLong": "707990" },
    "spell1Count": 0,
    "spell2Count": 0,
    "trueDmg": { "$numberLong": "415896" },
    "winCount": 250
  },
  {
    "_id": { "$oid": "5c3b64fb547a852e622831ea" },
    "key": 2,
    "winCount": 104,
    "lossCount": 130,
    "banCount": 30,
    "magicDmg": { "$numberLong": "116992" },
    "physDmg": { "$numberLong": "2588310" },
    "trueDmg": { "$numberLong": "1209591" },
    "spell1Count": 0,
    "spell2Count": 0,
    "killCount": 1506,
    "deathCount": 1547,
    "assistCount": 1628,
    "gameTime": { "$numberLong": "357136" }
  },
  {
    "_id": { "$oid": "5c3b64fb547a852e622831eb" },
    "key": 3,
    "winCount": 427,
    "lossCount": 618,
    "banCount": 657,
    "magicDmg": { "$numberLong": "16410850" },
    "physDmg": { "$numberLong": "507149" },
    "trueDmg": { "$numberLong": "556420" },
    "spell1Count": 0,
    "spell2Count": 0,
    "killCount": 5327,
    "deathCount": 6828,
    "assistCount": 9333,
    "gameTime": { "$numberLong": "1507119" }
  },
  {
    "_id": { "$oid": "5c3b64fb547a852e622831ec" },
    "key": 4,
    "winCount": 188,
    "lossCount": 193,
    "banCount": 17,
    "magicDmg": { "$numberLong": "6446739" },
    "physDmg": { "$numberLong": "806655" },
    "trueDmg": { "$numberLong": "229881" },
    "spell1Count": 0,
    "spell2Count": 0,
    "killCount": 2280,
    "deathCount": 2630,
    "assistCount": 4514,
    "gameTime": { "$numberLong": "569584" }
  },
  {
    "_id": { "$oid": "5c3b64fb547a852e622831ed" },
    "assistCount": 5336,
    "banCount": 237,
    "deathCount": 4662,
    "gameTime": { "$numberLong": "1140003" },
    "key": 5,
    "killCount": 4589,
    "lossCount": 346,
    "magicDmg": { "$numberLong": "954651" },
    "physDmg": { "$numberLong": "9122893" },
    "spell1Count": 0,
    "spell2Count": 0,
    "trueDmg": { "$numberLong": "636759" },
    "winCount": 365
  },
  {
    "_id": { "$oid": "5c3b64fb547a852e622831ee" },
    "assistCount": 3714,
    "banCount": 498,
    "deathCount": 2977,
    "gameTime": { "$numberLong": "837577" },
    "key": 6,
    "killCount": 3350,
    "lossCount": 243,
    "magicDmg": { "$numberLong": "203683" },
    "physDmg": { "$numberLong": "8227511" },
    "spell1Count": 0,
    "spell2Count": 0,
    "trueDmg": { "$numberLong": "762160" },
    "winCount": 272
  },
  {
    "_id": { "$oid": "5c3b64fb547a852e622831ef" },
    "key": 7,
    "winCount": 263,
    "lossCount": 310,
    "banCount": 804,
    "magicDmg": { "$numberLong": "9459782" },
    "physDmg": { "$numberLong": "809143" },
    "trueDmg": { "$numberLong": "443153" },
    "spell1Count": 0,
    "spell2Count": 0,
    "killCount": 4768,
    "deathCount": 3573,
    "assistCount": 5053,
    "gameTime": { "$numberLong": "878617" }
  },
  {
    "_id": { "$oid": "5c3b64fb547a852e622831f0" },
    "key": 8,
    "winCount": 219,
    "lossCount": 275,
    "banCount": 187,
    "magicDmg": { "$numberLong": "9171121" },
    "physDmg": { "$numberLong": "447384" },
    "trueDmg": { "$numberLong": "380649" },
    "spell1Count": 0,
    "spell2Count": 0,
    "killCount": 3081,
    "deathCount": 3137,
    "assistCount": 4117,
    "gameTime": { "$numberLong": "745895" }
  },
  {
    "_id": { "$oid": "5c3b64fb547a852e622831f1" },
    "key": 9,
    "winCount": 325,
    "lossCount": 290,
    "banCount": 152,
    "magicDmg": { "$numberLong": "10615498" },
    "physDmg": { "$numberLong": "325790" },
    "trueDmg": { "$numberLong": "368675" },
    "spell1Count": 0,
    "spell2Count": 0,
    "killCount": 3344,
    "deathCount": 4543,
    "assistCount": 8060,
    "gameTime": { "$numberLong": "901024" }
  },
  {
    "_id": { "$oid": "5c3b64fb547a852e622831f2" },
    "key": 10,
    "winCount": 135,
    "lossCount": 169,
    "banCount": 15,
    "magicDmg": { "$numberLong": "3122509" },
    "physDmg": { "$numberLong": "1316165" },
    "trueDmg": { "$numberLong": "158677" },
    "spell1Count": 0,
    "spell2Count": 0,
    "killCount": 1712,
    "deathCount": 2084,
    "assistCount": 3089,
    "gameTime": { "$numberLong": "432114" }
  },
  {
    "_id": { "$oid": "5c3b64fb547a852e622831f3" },
    "key": 11,
    "winCount": 890,
    "lossCount": 784,
    "banCount": 2002,
    "magicDmg": { "$numberLong": "804339" },
    "physDmg": { "$numberLong": "21064169" },
    "trueDmg": { "$numberLong": "6343500" },
    "spell1Count": 0,
    "spell2Count": 0,
    "killCount": 14380,
    "deathCount": 11889,
    "assistCount": 9009,
    "gameTime": { "$numberLong": "2563340" }
  },
  {
    "_id": { "$oid": "5c3b64fb547a852e622831f4" },
    "key": 12,
    "winCount": 230,
    "lossCount": 522,
    "banCount": 257,
    "magicDmg": { "$numberLong": "3828153" },
    "physDmg": { "$numberLong": "935388" },
    "trueDmg": { "$numberLong": "382395" },
    "spell1Count": 0,
    "spell2Count": 0,
    "killCount": 1482,
    "deathCount": 5454,
    "assistCount": 7924,
    "gameTime": { "$numberLong": "1015526" }
  },
  {
    "_id": { "$oid": "5c3b64fb547a852e622831f5" },
    "key": 13,
    "winCount": 170,
    "lossCount": 358,
    "banCount": 11,
    "magicDmg": { "$numberLong": "6704567" },
    "physDmg": { "$numberLong": "603803" },
    "trueDmg": { "$numberLong": "177580" },
    "spell1Count": 0,
    "spell2Count": 0,
    "killCount": 2475,
    "deathCount": 4164,
    "assistCount": 3445,
    "gameTime": { "$numberLong": "718295" }
  },
  {
    "_id": { "$oid": "5c3b64fb547a852e622831f6" },
    "key": 14,
    "winCount": 227,
    "lossCount": 226,
    "banCount": 69,
    "magicDmg": { "$numberLong": "2060619" },
    "physDmg": { "$numberLong": "5439725" },
    "trueDmg": { "$numberLong": "247661" },
    "spell1Count": 0,
    "spell2Count": 0,
    "killCount": 2427,
    "deathCount": 3162,
    "assistCount": 4593,
    "gameTime": { "$numberLong": "699064" }
  },
  {
    "_id": { "$oid": "5c3b64fb547a852e622831f7" },
    "key": 15,
    "winCount": 512,
    "lossCount": 472,
    "banCount": 32,
    "magicDmg": { "$numberLong": "476088" },
    "physDmg": { "$numberLong": "14657246" },
    "trueDmg": { "$numberLong": "598716" },
    "spell1Count": 0,
    "spell2Count": 0,
    "killCount": 5140,
    "deathCount": 5058,
    "assistCount": 7957,
    "gameTime": { "$numberLong": "1255823" }
  },
  {
    "_id": { "$oid": "5c3b64fb547a852e622831f8" },
    "key": 16,
    "winCount": 552,
    "lossCount": 369,
    "banCount": 99,
    "magicDmg": { "$numberLong": "5612615" },
    "physDmg": { "$numberLong": "711083" },
    "trueDmg": { "$numberLong": "377978" },
    "spell1Count": 0,
    "spell2Count": 0,
    "killCount": 1508,
    "deathCount": 4572,
    "assistCount": 12226,
    "gameTime": { "$numberLong": "1315316" }
  },
  {
    "_id": { "$oid": "5c3b64fb547a852e622831f9" },
    "key": 17,
    "winCount": 734,
    "lossCount": 612,
    "banCount": 791,
    "magicDmg": { "$numberLong": "27182696" },
    "physDmg": { "$numberLong": "3253987" },
    "trueDmg": { "$numberLong": "1297107" },
    "spell1Count": 0,
    "spell2Count": 0,
    "killCount": 9003,
    "deathCount": 9030,
    "assistCount": 12340,
    "gameTime": { "$numberLong": "2147607" }
  },
  {
    "_id": { "$oid": "5c3b64fb547a852e622831fa" },
    "key": 18,
    "winCount": 430,
    "lossCount": 454,
    "banCount": 60,
    "magicDmg": { "$numberLong": "2418281" },
    "physDmg": { "$numberLong": "12698734" },
    "trueDmg": { "$numberLong": "759304" },
    "spell1Count": 0,
    "spell2Count": 0,
    "killCount": 7047,
    "deathCount": 5785,
    "assistCount": 6871,
    "gameTime": { "$numberLong": "1361581" }
  },
  {
    "_id": { "$oid": "5c3b64fb547a852e622831fb" },
    "key": 19,
    "winCount": 358,
    "lossCount": 380,
    "banCount": 127,
    "magicDmg": { "$numberLong": "5029732" },
    "physDmg": { "$numberLong": "3572861" },
    "trueDmg": { "$numberLong": "678116" },
    "spell1Count": 0,
    "spell2Count": 0,
    "killCount": 4728,
    "deathCount": 5052,
    "assistCount": 5440,
    "gameTime": { "$numberLong": "1160354" }
  },
  {
    "_id": { "$oid": "5c3b64fb547a852e622831fc" },
    "key": 20,
    "winCount": 249,
    "lossCount": 257,
    "banCount": 45,
    "magicDmg": { "$numberLong": "5194950" },
    "physDmg": { "$numberLong": "707928" },
    "trueDmg": { "$numberLong": "310789" },
    "spell1Count": 0,
    "spell2Count": 0,
    "killCount": 2336,
    "deathCount": 3448,
    "assistCount": 6543,
    "gameTime": { "$numberLong": "727507" }
  },
  {
    "_id": { "$oid": "5c3b64fb547a852e622831fd" },
    "key": 21,
    "winCount": 1216,
    "lossCount": 793,
    "banCount": 413,
    "magicDmg": { "$numberLong": "4392998" },
    "physDmg": { "$numberLong": "31851467" },
    "trueDmg": { "$numberLong": "1432405" },
    "spell1Count": 0,
    "spell2Count": 0,
    "killCount": 15816,
    "deathCount": 11103,
    "assistCount": 15954,
    "gameTime": { "$numberLong": "2809988" }
  },
  {
    "_id": { "$oid": "5c3b64fb547a852e622831fe" },
    "key": 22,
    "winCount": 746,
    "lossCount": 578,
    "banCount": 56,
    "magicDmg": { "$numberLong": "2326617" },
    "physDmg": { "$numberLong": "18878594" },
    "trueDmg": { "$numberLong": "851714" },
    "spell1Count": 0,
    "spell2Count": 0,
    "killCount": 8033,
    "deathCount": 8330,
    "assistCount": 13485,
    "gameTime": { "$numberLong": "1967739" }
  },
  {
    "_id": { "$oid": "5c3b64fb547a852e622831ff" },
    "key": 23,
    "winCount": 207,
    "lossCount": 273,
    "banCount": 244,
    "magicDmg": { "$numberLong": "375276" },
    "physDmg": { "$numberLong": "6010776" },
    "trueDmg": { "$numberLong": "1302004" },
    "spell1Count": 0,
    "spell2Count": 0,
    "killCount": 2957,
    "deathCount": 3288,
    "assistCount": 2688,
    "gameTime": { "$numberLong": "777192" }
  },
  {
    "_id": { "$oid": "5c3b64fb547a852e62283200" },
    "key": 24,
    "winCount": 727,
    "lossCount": 680,
    "banCount": 1893,
    "magicDmg": { "$numberLong": "5116114" },
    "physDmg": { "$numberLong": "15180911" },
    "trueDmg": { "$numberLong": "2306266" },
    "spell1Count": 0,
    "spell2Count": 0,
    "killCount": 9949,
    "deathCount": 9108,
    "assistCount": 8063,
    "gameTime": { "$numberLong": "2310015" }
  },
  {
    "_id": { "$oid": "5c3b64fb547a852e62283201" },
    "key": 25,
    "winCount": 585,
    "lossCount": 713,
    "banCount": 1096,
    "magicDmg": { "$numberLong": "15692891" },
    "physDmg": { "$numberLong": "1413507" },
    "trueDmg": { "$numberLong": "777570" },
    "spell1Count": 0,
    "spell2Count": 0,
    "killCount": 4737,
    "deathCount": 8024,
    "assistCount": 16623,
    "gameTime": { "$numberLong": "1963217" }
  },
  {
    "_id": { "$oid": "5c3b64fb547a852e62283202" },
    "key": 26,
    "winCount": 201,
    "lossCount": 183,
    "banCount": 82,
    "magicDmg": { "$numberLong": "5559039" },
    "physDmg": { "$numberLong": "380461" },
    "trueDmg": { "$numberLong": "186736" },
    "spell1Count": 0,
    "spell2Count": 0,
    "killCount": 1615,
    "deathCount": 2428,
    "assistCount": 5839,
    "gameTime": { "$numberLong": "583941" }
  },
  {
    "_id": { "$oid": "5c3b64fb547a852e62283203" },
    "key": 27,
    "winCount": 149,
    "lossCount": 115,
    "banCount": 22,
    "magicDmg": { "$numberLong": "4802620" },
    "physDmg": { "$numberLong": "174495" },
    "trueDmg": { "$numberLong": "211790" },
    "spell1Count": 0,
    "spell2Count": 0,
    "killCount": 1431,
    "deathCount": 2146,
    "assistCount": 3649,
    "gameTime": { "$numberLong": "407296" }
  },
  {
    "_id": { "$oid": "5c3b64fb547a852e62283204" },
    "key": 28,
    "winCount": 173,
    "lossCount": 210,
    "banCount": 320,
    "magicDmg": { "$numberLong": "5745525" },
    "physDmg": { "$numberLong": "323881" },
    "trueDmg": { "$numberLong": "316804" },
    "spell1Count": 0,
    "spell2Count": 0,
    "killCount": 2867,
    "deathCount": 2414,
    "assistCount": 2717,
    "gameTime": { "$numberLong": "619734" }
  },
  {
    "_id": { "$oid": "5c3b64fb547a852e62283205" },
    "key": 29,
    "winCount": 404,
    "lossCount": 363,
    "banCount": 121,
    "magicDmg": { "$numberLong": "442170" },
    "physDmg": { "$numberLong": "12638590" },
    "trueDmg": { "$numberLong": "2470569" },
    "spell1Count": 0,
    "spell2Count": 0,
    "killCount": 6625,
    "deathCount": 5144,
    "assistCount": 7282,
    "gameTime": { "$numberLong": "1166058" }
  },
  {
    "_id": { "$oid": "5c3b64fb547a852e62283206" },
    "key": 30,
    "winCount": 237,
    "lossCount": 227,
    "banCount": 195,
    "magicDmg": { "$numberLong": "13026829" },
    "physDmg": { "$numberLong": "151198" },
    "trueDmg": { "$numberLong": "303869" },
    "spell1Count": 0,
    "spell2Count": 0,
    "killCount": 3879,
    "deathCount": 3646,
    "assistCount": 5880,
    "gameTime": { "$numberLong": "715574" }
  },
  {
    "_id": { "$oid": "5c3b64fb547a852e62283207" },
    "key": 31,
    "winCount": 195,
    "lossCount": 254,
    "banCount": 92,
    "magicDmg": { "$numberLong": "4854930" },
    "physDmg": { "$numberLong": "795151" },
    "trueDmg": { "$numberLong": "1486744" },
    "spell1Count": 0,
    "spell2Count": 0,
    "killCount": 2569,
    "deathCount": 3009,
    "assistCount": 4052,
    "gameTime": { "$numberLong": "642942" }
  },
  {
    "_id": { "$oid": "5c3b64fb547a852e62283208" },
    "key": 32,
    "winCount": 239,
    "lossCount": 222,
    "banCount": 77,
    "magicDmg": { "$numberLong": "5507960" },
    "physDmg": { "$numberLong": "623552" },
    "trueDmg": { "$numberLong": "719813" },
    "spell1Count": 0,
    "spell2Count": 0,
    "killCount": 2334,
    "deathCount": 3231,
    "assistCount": 5988,
    "gameTime": { "$numberLong": "700486" }
  },
  {
    "_id": { "$oid": "5c3b64fb547a852e62283209" },
    "key": 33,
    "winCount": 219,
    "lossCount": 243,
    "banCount": 241,
    "magicDmg": { "$numberLong": "4302109" },
    "physDmg": { "$numberLong": "1021878" },
    "trueDmg": { "$numberLong": "412351" },
    "spell1Count": 0,
    "spell2Count": 0,
    "killCount": 2029,
    "deathCount": 3085,
    "assistCount": 4851,
    "gameTime": { "$numberLong": "739714" }
  },
  {
    "_id": { "$oid": "5c3b64fb547a852e6228320a" },
    "key": 34,
    "winCount": 127,
    "lossCount": 118,
    "banCount": 52,
    "magicDmg": { "$numberLong": "4389099" },
    "physDmg": { "$numberLong": "219880" },
    "trueDmg": { "$numberLong": "168447" },
    "spell1Count": 0,
    "spell2Count": 0,
    "killCount": 1573,
    "deathCount": 1380,
    "assistCount": 3137,
    "gameTime": { "$numberLong": "364039" }
  },
  {
    "_id": { "$oid": "5c3b64fb547a852e6228320b" },
    "key": 35,
    "winCount": 278,
    "lossCount": 255,
    "banCount": 277,
    "magicDmg": { "$numberLong": "3155714" },
    "physDmg": { "$numberLong": "5004255" },
    "trueDmg": { "$numberLong": "666819" },
    "spell1Count": 0,
    "spell2Count": 0,
    "killCount": 3967,
    "deathCount": 3211,
    "assistCount": 4842,
    "gameTime": { "$numberLong": "868914" }
  },
  {
    "_id": { "$oid": "5c3b64fb547a852e6228320c" },
    "key": 36,
    "winCount": 151,
    "lossCount": 204,
    "banCount": 115,
    "magicDmg": { "$numberLong": "3974551" },
    "physDmg": { "$numberLong": "1717003" },
    "trueDmg": { "$numberLong": "216223" },
    "spell1Count": 0,
    "spell2Count": 0,
    "killCount": 1740,
    "deathCount": 2261,
    "assistCount": 3296,
    "gameTime": { "$numberLong": "525694" }
  },
  {
    "_id": { "$oid": "5c3b64fb547a852e6228320d" },
    "key": 37,
    "winCount": 449,
    "lossCount": 344,
    "banCount": 64,
    "magicDmg": { "$numberLong": "7997284" },
    "physDmg": { "$numberLong": "1400143" },
    "trueDmg": { "$numberLong": "408872" },
    "spell1Count": 0,
    "spell2Count": 0,
    "killCount": 2905,
    "deathCount": 4806,
    "assistCount": 12807,
    "gameTime": { "$numberLong": "1164914" }
  },
  {
    "_id": { "$oid": "5c3b64fb547a852e6228320e" },
    "key": 38,
    "winCount": 295,
    "lossCount": 311,
    "banCount": 378,
    "magicDmg": { "$numberLong": "9574000" },
    "physDmg": { "$numberLong": "1082290" },
    "trueDmg": { "$numberLong": "388675" },
    "spell1Count": 0,
    "spell2Count": 0,
    "killCount": 4900,
    "deathCount": 3907,
    "assistCount": 4436,
    "gameTime": { "$numberLong": "913003" }
  },
  {
    "_id": { "$oid": "5c3b64fb547a852e6228320f" },
    "key": 39,
    "winCount": 483,
    "lossCount": 474,
    "banCount": 1273,
    "magicDmg": { "$numberLong": "4429906" },
    "physDmg": { "$numberLong": "9670145" },
    "trueDmg": { "$numberLong": "2457575" },
    "spell1Count": 0,
    "spell2Count": 0,
    "killCount": 7712,
    "deathCount": 6747,
    "assistCount": 6184,
    "gameTime": { "$numberLong": "1514830" }
  },
  {
    "_id": { "$oid": "5c3b64fb547a852e62283210" },
    "key": 40,
    "winCount": 338,
    "lossCount": 282,
    "banCount": 45,
    "magicDmg": { "$numberLong": "5438836" },
    "physDmg": { "$numberLong": "577624" },
    "trueDmg": { "$numberLong": "350906" },
    "spell1Count": 0,
    "spell2Count": 0,
    "killCount": 1702,
    "deathCount": 3499,
    "assistCount": 9800,
    "gameTime": { "$numberLong": "953615" }
  },
  {
    "_id": { "$oid": "5c3b64fb547a852e62283211" },
    "key": 41,
    "winCount": 243,
    "lossCount": 268,
    "banCount": 68,
    "magicDmg": { "$numberLong": "1538667" },
    "physDmg": { "$numberLong": "6427741" },
    "trueDmg": { "$numberLong": "1200519" },
    "spell1Count": 0,
    "spell2Count": 0,
    "killCount": 3084,
    "deathCount": 3062,
    "assistCount": 4664,
    "gameTime": { "$numberLong": "758515" }
  },
  {
    "_id": { "$oid": "5c3b64fb547a852e62283212" },
    "key": 42,
    "winCount": 107,
    "lossCount": 95,
    "banCount": 36,
    "magicDmg": { "$numberLong": "3705081" },
    "physDmg": { "$numberLong": "485367" },
    "trueDmg": { "$numberLong": "130338" },
    "spell1Count": 0,
    "spell2Count": 0,
    "killCount": 1510,
    "deathCount": 1426,
    "assistCount": 2375,
    "gameTime": { "$numberLong": "286203" }
  },
  {
    "_id": { "$oid": "5c3b64fb547a852e62283213" },
    "key": 43,
    "winCount": 237,
    "lossCount": 244,
    "banCount": 35,
    "magicDmg": { "$numberLong": "6763558" },
    "physDmg": { "$numberLong": "617889" },
    "trueDmg": { "$numberLong": "300119" },
    "spell1Count": 0,
    "spell2Count": 0,
    "killCount": 2005,
    "deathCount": 2986,
    "assistCount": 7089,
    "gameTime": { "$numberLong": "743015" }
  },
  {
    "_id": { "$oid": "5c3b64fb547a852e62283214" },
    "key": 44,
    "winCount": 232,
    "lossCount": 163,
    "banCount": 15,
    "magicDmg": { "$numberLong": "1061173" },
    "physDmg": { "$numberLong": "691158" },
    "trueDmg": { "$numberLong": "115349" },
    "spell1Count": 0,
    "spell2Count": 0,
    "killCount": 725,
    "deathCount": 1922,
    "assistCount": 3939,
    "gameTime": { "$numberLong": "482596" }
  },
  {
    "_id": { "$oid": "5c3b64fb547a852e62283215" },
    "key": 45,
    "winCount": 574,
    "lossCount": 528,
    "banCount": 641,
    "magicDmg": { "$numberLong": "20467950" },
    "physDmg": { "$numberLong": "871788" },
    "trueDmg": { "$numberLong": "477402" },
    "spell1Count": 0,
    "spell2Count": 0,
    "killCount": 8055,
    "deathCount": 7264,
    "assistCount": 9873,
    "gameTime": { "$numberLong": "1718772" }
  },
  {
    "_id": { "$oid": "5c3b64fb547a852e62283216" },
    "key": 48,
    "winCount": 85,
    "lossCount": 177,
    "banCount": 21,
    "magicDmg": { "$numberLong": "496250" },
    "physDmg": { "$numberLong": "2008672" },
    "trueDmg": { "$numberLong": "189979" },
    "spell1Count": 0,
    "spell2Count": 0,
    "killCount": 1068,
    "deathCount": 1676,
    "assistCount": 1986,
    "gameTime": { "$numberLong": "360849" }
  },
  {
    "_id": { "$oid": "5c3b64fb547a852e62283217" },
    "key": 50,
    "winCount": 172,
    "lossCount": 130,
    "banCount": 36,
    "magicDmg": { "$numberLong": "6129721" },
    "physDmg": { "$numberLong": "553754" },
    "trueDmg": { "$numberLong": "231450" },
    "spell1Count": 0,
    "spell2Count": 0,
    "killCount": 2205,
    "deathCount": 1862,
    "assistCount": 4001,
    "gameTime": { "$numberLong": "445578" }
  },
  {
    "_id": { "$oid": "5c3b64fb547a852e62283218" },
    "key": 51,
    "winCount": 626,
    "lossCount": 627,
    "banCount": 389,
    "magicDmg": { "$numberLong": "1576918" },
    "physDmg": { "$numberLong": "21636505" },
    "trueDmg": { "$numberLong": "1131327" },
    "spell1Count": 0,
    "spell2Count": 0,
    "killCount": 8447,
    "deathCount": 7539,
    "assistCount": 10420,
    "gameTime": { "$numberLong": "1954331" }
  },
  {
    "_id": { "$oid": "5c3b64fb547a852e62283219" },
    "key": 53,
    "winCount": 625,
    "lossCount": 593,
    "banCount": 1258,
    "magicDmg": { "$numberLong": "7253131" },
    "physDmg": { "$numberLong": "3239955" },
    "trueDmg": { "$numberLong": "637600" },
    "spell1Count": 0,
    "spell2Count": 0,
    "killCount": 3677,
    "deathCount": 6332,
    "assistCount": 12255,
    "gameTime": { "$numberLong": "1661606" }
  },
  {
    "_id": { "$oid": "5c3b64fb547a852e6228321a" },
    "key": 54,
    "winCount": 284,
    "lossCount": 483,
    "banCount": 70,
    "magicDmg": { "$numberLong": "8581461" },
    "physDmg": { "$numberLong": "1720320" },
    "trueDmg": { "$numberLong": "380738" },
    "spell1Count": 0,
    "spell2Count": 0,
    "killCount": 3446,
    "deathCount": 4413,
    "assistCount": 6170,
    "gameTime": { "$numberLong": "1068359" }
  },
  {
    "_id": { "$oid": "5c3b64fb547a852e6228321b" },
    "key": 55,
    "winCount": 349,
    "lossCount": 371,
    "banCount": 326,
    "magicDmg": { "$numberLong": "12938049" },
    "physDmg": { "$numberLong": "1034577" },
    "trueDmg": { "$numberLong": "530178" },
    "spell1Count": 0,
    "spell2Count": 0,
    "killCount": 6749,
    "deathCount": 5340,
    "assistCount": 4938,
    "gameTime": { "$numberLong": "1105895" }
  },
  {
    "_id": { "$oid": "5c3b64fb547a852e6228321c" },
    "key": 56,
    "winCount": 234,
    "lossCount": 212,
    "banCount": 183,
    "magicDmg": { "$numberLong": "496319" },
    "physDmg": { "$numberLong": "5542578" },
    "trueDmg": { "$numberLong": "355364" },
    "spell1Count": 0,
    "spell2Count": 0,
    "killCount": 3122,
    "deathCount": 2958,
    "assistCount": 3266,
    "gameTime": { "$numberLong": "687410" }
  },
  {
    "_id": { "$oid": "5c3b64fb547a852e6228321d" },
    "key": 57,
    "winCount": 155,
    "lossCount": 122,
    "banCount": 79,
    "magicDmg": { "$numberLong": "4744236" },
    "physDmg": { "$numberLong": "556191" },
    "trueDmg": { "$numberLong": "196313" },
    "spell1Count": 0,
    "spell2Count": 0,
    "killCount": 1406,
    "deathCount": 1731,
    "assistCount": 4330,
    "gameTime": { "$numberLong": "385400" }
  },
  {
    "_id": { "$oid": "5c3b64fb547a852e6228321e" },
    "key": 58,
    "winCount": 514,
    "lossCount": 402,
    "banCount": 247,
    "magicDmg": { "$numberLong": "1172562" },
    "physDmg": { "$numberLong": "10374792" },
    "trueDmg": { "$numberLong": "781522" },
    "spell1Count": 0,
    "spell2Count": 0,
    "killCount": 4780,
    "deathCount": 5313,
    "assistCount": 5203,
    "gameTime": { "$numberLong": "1320432" }
  },
  {
    "_id": { "$oid": "5c3b64fb547a852e6228321f" },
    "key": 59,
    "winCount": 196,
    "lossCount": 177,
    "banCount": 54,
    "magicDmg": { "$numberLong": "649918" },
    "physDmg": { "$numberLong": "4692197" },
    "trueDmg": { "$numberLong": "343392" },
    "spell1Count": 0,
    "spell2Count": 0,
    "killCount": 2458,
    "deathCount": 2438,
    "assistCount": 5030,
    "gameTime": { "$numberLong": "586037" }
  },
  {
    "_id": { "$oid": "5c3b64fb547a852e62283220" },
    "key": 60,
    "winCount": 108,
    "lossCount": 101,
    "banCount": 46,
    "magicDmg": { "$numberLong": "3119124" },
    "physDmg": { "$numberLong": "243330" },
    "trueDmg": { "$numberLong": "199183" },
    "spell1Count": 0,
    "spell2Count": 0,
    "killCount": 1459,
    "deathCount": 1334,
    "assistCount": 1840,
    "gameTime": { "$numberLong": "342629" }
  },
  {
    "_id": { "$oid": "5c3b64fb547a852e62283221" },
    "key": 61,
    "winCount": 308,
    "lossCount": 356,
    "banCount": 46,
    "magicDmg": { "$numberLong": "10974147" },
    "physDmg": { "$numberLong": "692754" },
    "trueDmg": { "$numberLong": "326438" },
    "spell1Count": 0,
    "spell2Count": 0,
    "killCount": 3893,
    "deathCount": 4222,
    "assistCount": 7947,
    "gameTime": { "$numberLong": "996367" }
  },
  {
    "_id": { "$oid": "5c3b64fb547a852e62283222" },
    "key": 62,
    "winCount": 195,
    "lossCount": 189,
    "banCount": 88,
    "magicDmg": { "$numberLong": "181464" },
    "physDmg": { "$numberLong": "6582860" },
    "trueDmg": { "$numberLong": "355414" },
    "spell1Count": 0,
    "spell2Count": 0,
    "killCount": 3147,
    "deathCount": 2612,
    "assistCount": 3119,
    "gameTime": { "$numberLong": "587148" }
  },
  {
    "_id": { "$oid": "5c3b64fb547a852e62283223" },
    "key": 63,
    "winCount": 703,
    "lossCount": 503,
    "banCount": 1882,
    "magicDmg": { "$numberLong": "22974253" },
    "physDmg": { "$numberLong": "1176919" },
    "trueDmg": { "$numberLong": "817094" },
    "spell1Count": 0,
    "spell2Count": 0,
    "killCount": 7635,
    "deathCount": 7766,
    "assistCount": 11654,
    "gameTime": { "$numberLong": "1816737" }
  },
  {
    "_id": { "$oid": "5c3b64fb547a852e62283224" },
    "key": 64,
    "winCount": 770,
    "lossCount": 852,
    "banCount": 842,
    "magicDmg": { "$numberLong": "3992042" },
    "physDmg": { "$numberLong": "19224559" },
    "trueDmg": { "$numberLong": "1145279" },
    "spell1Count": 0,
    "spell2Count": 0,
    "killCount": 12248,
    "deathCount": 10527,
    "assistCount": 13457,
    "gameTime": { "$numberLong": "2631929" }
  },
  {
    "_id": { "$oid": "5c3b64fb547a852e62283225" },
    "key": 67,
    "winCount": 794,
    "lossCount": 814,
    "banCount": 630,
    "magicDmg": { "$numberLong": "1364424" },
    "physDmg": { "$numberLong": "21059457" },
    "trueDmg": { "$numberLong": "7043894" },
    "spell1Count": 0,
    "spell2Count": 0,
    "killCount": 12349,
    "deathCount": 10561,
    "assistCount": 10637,
    "gameTime": { "$numberLong": "2515340" }
  },
  {
    "_id": { "$oid": "5c3b64fb547a852e62283226" },
    "key": 68,
    "winCount": 92,
    "lossCount": 96,
    "banCount": 18,
    "magicDmg": { "$numberLong": "3801656" },
    "physDmg": { "$numberLong": "151498" },
    "trueDmg": { "$numberLong": "124589" },
    "spell1Count": 0,
    "spell2Count": 0,
    "killCount": 1378,
    "deathCount": 1331,
    "assistCount": 1968,
    "gameTime": { "$numberLong": "279156" }
  },
  {
    "_id": { "$oid": "5c3b64fb547a852e62283227" },
    "key": 69,
    "winCount": 278,
    "lossCount": 251,
    "banCount": 345,
    "magicDmg": { "$numberLong": "10668183" },
    "physDmg": { "$numberLong": "392369" },
    "trueDmg": { "$numberLong": "336805" },
    "spell1Count": 0,
    "spell2Count": 0,
    "killCount": 3741,
    "deathCount": 3570,
    "assistCount": 6029,
    "gameTime": { "$numberLong": "803721" }
  },
  {
    "_id": { "$oid": "5c3b64fb547a852e62283228" },
    "key": 72,
    "winCount": 41,
    "lossCount": 41,
    "banCount": 5,
    "magicDmg": { "$numberLong": "290425" },
    "physDmg": { "$numberLong": "586590" },
    "trueDmg": { "$numberLong": "104158" },
    "spell1Count": 0,
    "spell2Count": 0,
    "killCount": 406,
    "deathCount": 517,
    "assistCount": 1022,
    "gameTime": { "$numberLong": "129751" }
  },
  {
    "_id": { "$oid": "5c3b64fb547a852e62283229" },
    "key": 74,
    "winCount": 283,
    "lossCount": 244,
    "banCount": 132,
    "magicDmg": { "$numberLong": "12829593" },
    "physDmg": { "$numberLong": "480815" },
    "trueDmg": { "$numberLong": "254927" },
    "spell1Count": 0,
    "spell2Count": 0,
    "killCount": 3592,
    "deathCount": 3612,
    "assistCount": 7114,
    "gameTime": { "$numberLong": "764285" }
  },
  {
    "_id": { "$oid": "5c3b64fb547a852e6228322a" },
    "key": 75,
    "winCount": 649,
    "lossCount": 953,
    "banCount": 714,
    "magicDmg": { "$numberLong": "9728323" },
    "physDmg": { "$numberLong": "13363976" },
    "trueDmg": { "$numberLong": "926382" },
    "spell1Count": 0,
    "spell2Count": 0,
    "killCount": 7857,
    "deathCount": 9416,
    "assistCount": 10003,
    "gameTime": { "$numberLong": "2296638" }
  },
  {
    "_id": { "$oid": "5c3b64fb547a852e6228322b" },
    "key": 76,
    "winCount": 173,
    "lossCount": 248,
    "banCount": 39,
    "magicDmg": { "$numberLong": "6929252" },
    "physDmg": { "$numberLong": "396169" },
    "trueDmg": { "$numberLong": "211996" },
    "spell1Count": 0,
    "spell2Count": 0,
    "killCount": 2966,
    "deathCount": 2735,
    "assistCount": 4352,
    "gameTime": { "$numberLong": "635159" }
  },
  {
    "_id": { "$oid": "5c3b64fb547a852e6228322c" },
    "key": 77,
    "winCount": 232,
    "lossCount": 199,
    "banCount": 190,
    "magicDmg": { "$numberLong": "193249" },
    "physDmg": { "$numberLong": "4776396" },
    "trueDmg": { "$numberLong": "542085" },
    "spell1Count": 0,
    "spell2Count": 0,
    "killCount": 2633,
    "deathCount": 2682,
    "assistCount": 2701,
    "gameTime": { "$numberLong": "699265" }
  },
  {
    "_id": { "$oid": "5c3b64fb547a852e6228322d" },
    "key": 78,
    "winCount": 209,
    "lossCount": 221,
    "banCount": 70,
    "magicDmg": { "$numberLong": "1333991" },
    "physDmg": { "$numberLong": "4806268" },
    "trueDmg": { "$numberLong": "276778" },
    "spell1Count": 0,
    "spell2Count": 0,
    "killCount": 2208,
    "deathCount": 2540,
    "assistCount": 4152,
    "gameTime": { "$numberLong": "653462" }
  },
  {
    "_id": { "$oid": "5c3b64fb547a852e6228322e" },
    "key": 79,
    "winCount": 224,
    "lossCount": 265,
    "banCount": 42,
    "magicDmg": { "$numberLong": "7232488" },
    "physDmg": { "$numberLong": "734368" },
    "trueDmg": { "$numberLong": "399975" },
    "spell1Count": 0,
    "spell2Count": 0,
    "killCount": 2803,
    "deathCount": 3416,
    "assistCount": 5775,
    "gameTime": { "$numberLong": "741024" }
  },
  {
    "_id": { "$oid": "5c3b64fb547a852e6228322f" },
    "key": 80,
    "winCount": 242,
    "lossCount": 305,
    "banCount": 206,
    "magicDmg": { "$numberLong": "1274597" },
    "physDmg": { "$numberLong": "7469785" },
    "trueDmg": { "$numberLong": "485815" },
    "spell1Count": 0,
    "spell2Count": 0,
    "killCount": 4239,
    "deathCount": 3927,
    "assistCount": 4123,
    "gameTime": { "$numberLong": "887284" }
  },
  {
    "_id": { "$oid": "5c3b64fb547a852e62283230" },
    "key": 81,
    "winCount": 871,
    "lossCount": 1066,
    "banCount": 342,
    "magicDmg": { "$numberLong": "14034635" },
    "physDmg": { "$numberLong": "24902891" },
    "trueDmg": { "$numberLong": "802941" },
    "spell1Count": 0,
    "spell2Count": 0,
    "killCount": 12170,
    "deathCount": 11370,
    "assistCount": 15284,
    "gameTime": { "$numberLong": "2999906" }
  },
  {
    "_id": { "$oid": "5c3b64fb547a852e62283231" },
    "key": 82,
    "winCount": 234,
    "lossCount": 208,
    "banCount": 206,
    "magicDmg": { "$numberLong": "7623284" },
    "physDmg": { "$numberLong": "774161" },
    "trueDmg": { "$numberLong": "332714" },
    "spell1Count": 0,
    "spell2Count": 0,
    "killCount": 2880,
    "deathCount": 2895,
    "assistCount": 3097,
    "gameTime": { "$numberLong": "694428" }
  },
  {
    "_id": { "$oid": "5c3b64fb547a852e62283232" },
    "key": 83,
    "winCount": 126,
    "lossCount": 89,
    "banCount": 50,
    "magicDmg": { "$numberLong": "1205126" },
    "physDmg": { "$numberLong": "2439156" },
    "trueDmg": { "$numberLong": "290456" },
    "spell1Count": 0,
    "spell2Count": 0,
    "killCount": 1306,
    "deathCount": 1407,
    "assistCount": 2019,
    "gameTime": { "$numberLong": "312339" }
  },
  {
    "_id": { "$oid": "5c3b64fb547a852e62283233" },
    "key": 84,
    "winCount": 403,
    "lossCount": 510,
    "banCount": 1898,
    "magicDmg": { "$numberLong": "10971294" },
    "physDmg": { "$numberLong": "3293194" },
    "trueDmg": { "$numberLong": "632937" },
    "spell1Count": 0,
    "spell2Count": 0,
    "killCount": 6782,
    "deathCount": 5959,
    "assistCount": 5359,
    "gameTime": { "$numberLong": "1436535" }
  },
  {
    "_id": { "$oid": "5c3b64fb547a852e62283234" },
    "key": 85,
    "winCount": 130,
    "lossCount": 124,
    "banCount": 33,
    "magicDmg": { "$numberLong": "4319044" },
    "physDmg": { "$numberLong": "595304" },
    "trueDmg": { "$numberLong": "169720" },
    "spell1Count": 0,
    "spell2Count": 0,
    "killCount": 1613,
    "deathCount": 1768,
    "assistCount": 2736,
    "gameTime": { "$numberLong": "373308" }
  },
  {
    "_id": { "$oid": "5c3b64fb547a852e62283235" },
    "key": 86,
    "winCount": 568,
    "lossCount": 514,
    "banCount": 516,
    "magicDmg": { "$numberLong": "2920088" },
    "physDmg": { "$numberLong": "12160406" },
    "trueDmg": { "$numberLong": "2164224" },
    "spell1Count": 0,
    "spell2Count": 0,
    "killCount": 6952,
    "deathCount": 5925,
    "assistCount": 6669,
    "gameTime": { "$numberLong": "1679317" }
  },
  {
    "_id": { "$oid": "5c3b64fb547a852e62283236" },
    "key": 89,
    "winCount": 361,
    "lossCount": 389,
    "banCount": 475,
    "magicDmg": { "$numberLong": "3394718" },
    "physDmg": { "$numberLong": "1963324" },
    "trueDmg": { "$numberLong": "499793" },
    "spell1Count": 0,
    "spell2Count": 0,
    "killCount": 1947,
    "deathCount": 4785,
    "assistCount": 9386,
    "gameTime": { "$numberLong": "1183489" }
  },
  {
    "_id": { "$oid": "5c3b64fb547a852e62283237" },
    "key": 90,
    "winCount": 184,
    "lossCount": 173,
    "banCount": 230,
    "magicDmg": { "$numberLong": "7260420" },
    "physDmg": { "$numberLong": "260968" },
    "trueDmg": { "$numberLong": "259995" },
    "spell1Count": 0,
    "spell2Count": 0,
    "killCount": 2115,
    "deathCount": 2109,
    "assistCount": 3911,
    "gameTime": { "$numberLong": "560046" }
  },
  {
    "_id": { "$oid": "5c3b64fb547a852e62283238" },
    "key": 91,
    "winCount": 290,
    "lossCount": 281,
    "banCount": 175,
    "magicDmg": { "$numberLong": "54503" },
    "physDmg": { "$numberLong": "10378793" },
    "trueDmg": { "$numberLong": "510927" },
    "spell1Count": 0,
    "spell2Count": 0,
    "killCount": 4981,
    "deathCount": 4313,
    "assistCount": 4274,
    "gameTime": { "$numberLong": "905643" }
  },
  {
    "_id": { "$oid": "5c3b64fb547a852e62283239" },
    "key": 92,
    "winCount": 458,
    "lossCount": 427,
    "banCount": 208,
    "magicDmg": { "$numberLong": "66389" },
    "physDmg": { "$numberLong": "12612279" },
    "trueDmg": { "$numberLong": "1249891" },
    "spell1Count": 0,
    "spell2Count": 0,
    "killCount": 6337,
    "deathCount": 5506,
    "assistCount": 5200,
    "gameTime": { "$numberLong": "1395423" }
  },
  {
    "_id": { "$oid": "5c3b64fb547a852e6228323a" },
    "key": 96,
    "winCount": 292,
    "lossCount": 251,
    "banCount": 27,
    "magicDmg": { "$numberLong": "6393077" },
    "physDmg": { "$numberLong": "4939737" },
    "trueDmg": { "$numberLong": "1556379" },
    "spell1Count": 0,
    "spell2Count": 0,
    "killCount": 4935,
    "deathCount": 4088,
    "assistCount": 5680,
    "gameTime": { "$numberLong": "787049" }
  },
  {
    "_id": { "$oid": "5c3b64fb547a852e6228323b" },
    "key": 98,
    "winCount": 395,
    "lossCount": 246,
    "banCount": 24,
    "magicDmg": { "$numberLong": "2151278" },
    "physDmg": { "$numberLong": "3124917" },
    "trueDmg": { "$numberLong": "253183" },
    "spell1Count": 0,
    "spell2Count": 0,
    "killCount": 2075,
    "deathCount": 3118,
    "assistCount": 6151,
    "gameTime": { "$numberLong": "870011" }
  },
  {
    "_id": { "$oid": "5c3b64fb547a852e6228323c" },
    "key": 99,
    "winCount": 1044,
    "lossCount": 946,
    "banCount": 487,
    "magicDmg": { "$numberLong": "34927499" },
    "physDmg": { "$numberLong": "2427652" },
    "trueDmg": { "$numberLong": "995988" },
    "spell1Count": 0,
    "spell2Count": 0,
    "killCount": 12555,
    "deathCount": 11785,
    "assistCount": 22430,
    "gameTime": { "$numberLong": "3147749" }
  },
  {
    "_id": { "$oid": "5c3b64fb547a852e6228323d" },
    "key": 101,
    "winCount": 263,
    "lossCount": 227,
    "banCount": 54,
    "magicDmg": { "$numberLong": "11258284" },
    "physDmg": { "$numberLong": "294403" },
    "trueDmg": { "$numberLong": "214145" },
    "spell1Count": 0,
    "spell2Count": 0,
    "killCount": 3408,
    "deathCount": 2794,
    "assistCount": 5891,
    "gameTime": { "$numberLong": "747232" }
  },
  {
    "_id": { "$oid": "5c3b64fb547a852e6228323e" },
    "key": 102,
    "winCount": 142,
    "lossCount": 168,
    "banCount": 17,
    "magicDmg": { "$numberLong": "3343876" },
    "physDmg": { "$numberLong": "1407539" },
    "trueDmg": { "$numberLong": "294726" },
    "spell1Count": 0,
    "spell2Count": 0,
    "killCount": 1786,
    "deathCount": 1901,
    "assistCount": 2454,
    "gameTime": { "$numberLong": "479897" }
  },
  {
    "_id": { "$oid": "5c3b64fb547a852e6228323f" },
    "key": 103,
    "winCount": 535,
    "lossCount": 502,
    "banCount": 368,
    "magicDmg": { "$numberLong": "13226396" },
    "physDmg": { "$numberLong": "1536825" },
    "trueDmg": { "$numberLong": "4986834" },
    "spell1Count": 0,
    "spell2Count": 0,
    "killCount": 6980,
    "deathCount": 6162,
    "assistCount": 9103,
    "gameTime": { "$numberLong": "1601230" }
  },
  {
    "_id": { "$oid": "5c3b64fb547a852e62283240" },
    "key": 104,
    "winCount": 340,
    "lossCount": 320,
    "banCount": 157,
    "magicDmg": { "$numberLong": "882983" },
    "physDmg": { "$numberLong": "11071104" },
    "trueDmg": { "$numberLong": "572671" },
    "spell1Count": 0,
    "spell2Count": 0,
    "killCount": 5036,
    "deathCount": 4349,
    "assistCount": 6868,
    "gameTime": { "$numberLong": "962836" }
  },
  {
    "_id": { "$oid": "5c3b64fb547a852e62283241" },
    "key": 105,
    "winCount": 278,
    "lossCount": 276,
    "banCount": 609,
    "magicDmg": { "$numberLong": "7960796" },
    "physDmg": { "$numberLong": "1548715" },
    "trueDmg": { "$numberLong": "496235" },
    "spell1Count": 0,
    "spell2Count": 0,
    "killCount": 5014,
    "deathCount": 3806,
    "assistCount": 4210,
    "gameTime": { "$numberLong": "845344" }
  },
  {
    "_id": { "$oid": "5c3b64fb547a852e62283242" },
    "key": 106,
    "winCount": 181,
    "lossCount": 176,
    "banCount": 28,
    "magicDmg": { "$numberLong": "2251477" },
    "physDmg": { "$numberLong": "2460404" },
    "trueDmg": { "$numberLong": "304381" },
    "spell1Count": 0,
    "spell2Count": 0,
    "killCount": 2084,
    "deathCount": 2378,
    "assistCount": 4031,
    "gameTime": { "$numberLong": "524126" }
  },
  {
    "_id": { "$oid": "5c3b64fb547a852e62283243" },
    "key": 107,
    "winCount": 307,
    "lossCount": 306,
    "banCount": 297,
    "magicDmg": { "$numberLong": "965852" },
    "physDmg": { "$numberLong": "8958625" },
    "trueDmg": { "$numberLong": "450649" },
    "spell1Count": 0,
    "spell2Count": 0,
    "killCount": 5000,
    "deathCount": 4326,
    "assistCount": 3832,
    "gameTime": { "$numberLong": "966605" }
  },
  {
    "_id": { "$oid": "5c3b64fb547a852e62283244" },
    "key": 110,
    "winCount": 313,
    "lossCount": 331,
    "banCount": 40,
    "magicDmg": { "$numberLong": "2351168" },
    "physDmg": { "$numberLong": "10751753" },
    "trueDmg": { "$numberLong": "264485" },
    "spell1Count": 0,
    "spell2Count": 0,
    "killCount": 4890,
    "deathCount": 4472,
    "assistCount": 7457,
    "gameTime": { "$numberLong": "976754" }
  },
  {
    "_id": { "$oid": "5c3b64fb547a852e62283245" },
    "key": 111,
    "winCount": 212,
    "lossCount": 218,
    "banCount": 37,
    "magicDmg": { "$numberLong": "3852178" },
    "physDmg": { "$numberLong": "1122029" },
    "trueDmg": { "$numberLong": "291500" },
    "spell1Count": 0,
    "spell2Count": 0,
    "killCount": 1621,
    "deathCount": 2929,
    "assistCount": 6256,
    "gameTime": { "$numberLong": "646847" }
  },
  {
    "_id": { "$oid": "5c3b64fb547a852e62283246" },
    "key": 112,
    "winCount": 169,
    "lossCount": 160,
    "banCount": 85,
    "magicDmg": { "$numberLong": "6915311" },
    "physDmg": { "$numberLong": "281613" },
    "trueDmg": { "$numberLong": "136302" },
    "spell1Count": 0,
    "spell2Count": 0,
    "killCount": 2052,
    "deathCount": 2132,
    "assistCount": 3231,
    "gameTime": { "$numberLong": "511121" }
  },
  {
    "_id": { "$oid": "5c3b64fb547a852e62283247" },
    "key": 113,
    "winCount": 125,
    "lossCount": 146,
    "banCount": 54,
    "magicDmg": { "$numberLong": "1490615" },
    "physDmg": { "$numberLong": "1599266" },
    "trueDmg": { "$numberLong": "270415" },
    "spell1Count": 0,
    "spell2Count": 0,
    "killCount": 1304,
    "deathCount": 1398,
    "assistCount": 2883,
    "gameTime": { "$numberLong": "435215" }
  },
  {
    "_id": { "$oid": "5c3b64fb547a852e62283248" },
    "key": 114,
    "winCount": 218,
    "lossCount": 219,
    "banCount": 348,
    "magicDmg": { "$numberLong": "381163" },
    "physDmg": { "$numberLong": "5246729" },
    "trueDmg": { "$numberLong": "2460575" },
    "spell1Count": 0,
    "spell2Count": 0,
    "killCount": 3122,
    "deathCount": 2931,
    "assistCount": 2486,
    "gameTime": { "$numberLong": "720064" }
  },
  {
    "_id": { "$oid": "5c3b64fb547a852e62283249" },
    "key": 115,
    "winCount": 307,
    "lossCount": 194,
    "banCount": 38,
    "magicDmg": { "$numberLong": "13435407" },
    "physDmg": { "$numberLong": "471184" },
    "trueDmg": { "$numberLong": "243955" },
    "spell1Count": 0,
    "spell2Count": 0,
    "killCount": 3842,
    "deathCount": 2969,
    "assistCount": 7621,
    "gameTime": { "$numberLong": "690292" }
  },
  {
    "_id": { "$oid": "5c3b64fb547a852e6228324a" },
    "key": 117,
    "winCount": 312,
    "lossCount": 299,
    "banCount": 161,
    "magicDmg": { "$numberLong": "4095481" },
    "physDmg": { "$numberLong": "1033049" },
    "trueDmg": { "$numberLong": "369842" },
    "spell1Count": 0,
    "spell2Count": 0,
    "killCount": 1774,
    "deathCount": 3542,
    "assistCount": 9826,
    "gameTime": { "$numberLong": "933647" }
  },
  {
    "_id": { "$oid": "5c3b64fb547a852e6228324b" },
    "key": 119,
    "winCount": 433,
    "lossCount": 452,
    "banCount": 1167,
    "magicDmg": { "$numberLong": "485896" },
    "physDmg": { "$numberLong": "15472811" },
    "trueDmg": { "$numberLong": "1354534" },
    "spell1Count": 0,
    "spell2Count": 0,
    "killCount": 6970,
    "deathCount": 6198,
    "assistCount": 6861,
    "gameTime": { "$numberLong": "1356236" }
  },
  {
    "_id": { "$oid": "5c3b64fb547a852e6228324c" },
    "key": 120,
    "winCount": 129,
    "lossCount": 134,
    "banCount": 69,
    "magicDmg": { "$numberLong": "750910" },
    "physDmg": { "$numberLong": "3243192" },
    "trueDmg": { "$numberLong": "305521" },
    "spell1Count": 0,
    "spell2Count": 0,
    "killCount": 2006,
    "deathCount": 1822,
    "assistCount": 2413,
    "gameTime": { "$numberLong": "410415" }
  },
  {
    "_id": { "$oid": "5c3b64fb547a852e6228324d" },
    "key": 121,
    "winCount": 418,
    "lossCount": 383,
    "banCount": 507,
    "magicDmg": { "$numberLong": "904345" },
    "physDmg": { "$numberLong": "11664529" },
    "trueDmg": { "$numberLong": "625602" },
    "spell1Count": 0,
    "spell2Count": 0,
    "killCount": 6659,
    "deathCount": 4820,
    "assistCount": 4854,
    "gameTime": { "$numberLong": "1299806" }
  },
  {
    "_id": { "$oid": "5c3b64fb547a852e6228324e" },
    "key": 122,
    "winCount": 785,
    "lossCount": 652,
    "banCount": 2727,
    "magicDmg": { "$numberLong": "447110" },
    "physDmg": { "$numberLong": "17719630" },
    "trueDmg": { "$numberLong": "4570343" },
    "spell1Count": 0,
    "spell2Count": 0,
    "killCount": 10148,
    "deathCount": 8813,
    "assistCount": 8624,
    "gameTime": { "$numberLong": "2179473" }
  },
  {
    "_id": { "$oid": "5c3b64fb547a852e6228324f" },
    "key": 126,
    "winCount": 161,
    "lossCount": 170,
    "banCount": 51,
    "magicDmg": { "$numberLong": "1092888" },
    "physDmg": { "$numberLong": "5870932" },
    "trueDmg": { "$numberLong": "190695" },
    "spell1Count": 0,
    "spell2Count": 0,
    "killCount": 2670,
    "deathCount": 2025,
    "assistCount": 3609,
    "gameTime": { "$numberLong": "478323" }
  },
  {
    "_id": { "$oid": "5c3b64fb547a852e62283250" },
    "key": 127,
    "winCount": 187,
    "lossCount": 135,
    "banCount": 157,
    "magicDmg": { "$numberLong": "5752093" },
    "physDmg": { "$numberLong": "370453" },
    "trueDmg": { "$numberLong": "181041" },
    "spell1Count": 0,
    "spell2Count": 0,
    "killCount": 1939,
    "deathCount": 1978,
    "assistCount": 3799,
    "gameTime": { "$numberLong": "484838" }
  },
  {
    "_id": { "$oid": "5c3b64fb547a852e62283251" },
    "key": 131,
    "winCount": 225,
    "lossCount": 223,
    "banCount": 271,
    "magicDmg": { "$numberLong": "7732830" },
    "physDmg": { "$numberLong": "828985" },
    "trueDmg": { "$numberLong": "382097" },
    "spell1Count": 0,
    "spell2Count": 0,
    "killCount": 3681,
    "deathCount": 3073,
    "assistCount": 3327,
    "gameTime": { "$numberLong": "707207" }
  },
  {
    "_id": { "$oid": "5c3b64fb547a852e62283252" },
    "key": 133,
    "winCount": 114,
    "lossCount": 129,
    "banCount": 47,
    "magicDmg": { "$numberLong": "263521" },
    "physDmg": { "$numberLong": "4288804" },
    "trueDmg": { "$numberLong": "220826" },
    "spell1Count": 0,
    "spell2Count": 0,
    "killCount": 1881,
    "deathCount": 1988,
    "assistCount": 2176,
    "gameTime": { "$numberLong": "386395" }
  },
  {
    "_id": { "$oid": "5c3b64fb547a852e62283253" },
    "key": 134,
    "winCount": 127,
    "lossCount": 140,
    "banCount": 35,
    "magicDmg": { "$numberLong": "5126339" },
    "physDmg": { "$numberLong": "223837" },
    "trueDmg": { "$numberLong": "209551" },
    "spell1Count": 0,
    "spell2Count": 0,
    "killCount": 1829,
    "deathCount": 1857,
    "assistCount": 2573,
    "gameTime": { "$numberLong": "407369" }
  },
  {
    "_id": { "$oid": "5c3b64fb547a852e62283254" },
    "key": 136,
    "winCount": 75,
    "lossCount": 77,
    "banCount": 35,
    "magicDmg": { "$numberLong": "2705962" },
    "physDmg": { "$numberLong": "172309" },
    "trueDmg": { "$numberLong": "88403" },
    "spell1Count": 0,
    "spell2Count": 0,
    "killCount": 940,
    "deathCount": 1168,
    "assistCount": 2146,
    "gameTime": { "$numberLong": "214056" }
  },
  {
    "_id": { "$oid": "5c3b64fb547a852e62283255" },
    "key": 141,
    "winCount": 526,
    "lossCount": 491,
    "banCount": 581,
    "magicDmg": { "$numberLong": "1320763" },
    "physDmg": { "$numberLong": "14803225" },
    "trueDmg": { "$numberLong": "975784" },
    "spell1Count": 0,
    "spell2Count": 0,
    "killCount": 7402,
    "deathCount": 6875,
    "assistCount": 7549,
    "gameTime": { "$numberLong": "1671692" }
  },
  {
    "_id": { "$oid": "5c3b64fb547a852e62283256" },
    "key": 142,
    "winCount": 264,
    "lossCount": 276,
    "banCount": 323,
    "magicDmg": { "$numberLong": "8498674" },
    "physDmg": { "$numberLong": "860975" },
    "trueDmg": { "$numberLong": "1435588" },
    "spell1Count": 0,
    "spell2Count": 0,
    "killCount": 3471,
    "deathCount": 3343,
    "assistCount": 5156,
    "gameTime": { "$numberLong": "817077" }
  },
  {
    "_id": { "$oid": "5c3b64fb547a852e62283257" },
    "key": 143,
    "winCount": 337,
    "lossCount": 302,
    "banCount": 403,
    "magicDmg": { "$numberLong": "12740421" },
    "physDmg": { "$numberLong": "662378" },
    "trueDmg": { "$numberLong": "542632" },
    "spell1Count": 0,
    "spell2Count": 0,
    "killCount": 3312,
    "deathCount": 4196,
    "assistCount": 7763,
    "gameTime": { "$numberLong": "1010843" }
  },
  {
    "_id": { "$oid": "5c3b64fb547a852e62283258" },
    "key": 145,
    "winCount": 642,
    "lossCount": 601,
    "banCount": 433,
    "magicDmg": { "$numberLong": "8333929" },
    "physDmg": { "$numberLong": "14397245" },
    "trueDmg": { "$numberLong": "606249" },
    "spell1Count": 0,
    "spell2Count": 0,
    "killCount": 9974,
    "deathCount": 7487,
    "assistCount": 9443,
    "gameTime": { "$numberLong": "2018389" }
  },
  {
    "_id": { "$oid": "5c3b64fb547a852e62283259" },
    "key": 150,
    "winCount": 107,
    "lossCount": 113,
    "banCount": 40,
    "magicDmg": { "$numberLong": "606088" },
    "physDmg": { "$numberLong": "3225596" },
    "trueDmg": { "$numberLong": "140276" },
    "spell1Count": 0,
    "spell2Count": 0,
    "killCount": 1241,
    "deathCount": 1456,
    "assistCount": 2124,
    "gameTime": { "$numberLong": "347541" }
  },
  {
    "_id": { "$oid": "5c3b64fb547a852e6228325a" },
    "key": 154,
    "winCount": 84,
    "lossCount": 103,
    "banCount": 21,
    "magicDmg": { "$numberLong": "1861839" },
    "physDmg": { "$numberLong": "230053" },
    "trueDmg": { "$numberLong": "222672" },
    "spell1Count": 0,
    "spell2Count": 0,
    "killCount": 854,
    "deathCount": 1001,
    "assistCount": 2440,
    "gameTime": { "$numberLong": "290098" }
  },
  {
    "_id": { "$oid": "5c3b64fb547a852e6228325b" },
    "key": 157,
    "winCount": 1316,
    "lossCount": 1211,
    "banCount": 3080,
    "magicDmg": { "$numberLong": "3764814" },
    "physDmg": { "$numberLong": "35395149" },
    "trueDmg": { "$numberLong": "9668309" },
    "spell1Count": 0,
    "spell2Count": 0,
    "killCount": 20087,
    "deathCount": 18331,
    "assistCount": 15042,
    "gameTime": { "$numberLong": "4050775" }
  },
  {
    "_id": { "$oid": "5c3b64fb547a852e6228325c" },
    "key": 161,
    "winCount": 269,
    "lossCount": 214,
    "banCount": 75,
    "magicDmg": { "$numberLong": "9887179" },
    "physDmg": { "$numberLong": "300993" },
    "trueDmg": { "$numberLong": "2507172" },
    "spell1Count": 0,
    "spell2Count": 0,
    "killCount": 3585,
    "deathCount": 3143,
    "assistCount": 6286,
    "gameTime": { "$numberLong": "754653" }
  },
  {
    "_id": { "$oid": "5c3b64fb547a852e6228325d" },
    "key": 163,
    "winCount": 95,
    "lossCount": 137,
    "banCount": 18,
    "magicDmg": { "$numberLong": "4598849" },
    "physDmg": { "$numberLong": "192378" },
    "trueDmg": { "$numberLong": "168475" },
    "spell1Count": 0,
    "spell2Count": 0,
    "killCount": 1582,
    "deathCount": 1861,
    "assistCount": 3294,
    "gameTime": { "$numberLong": "317131" }
  },
  {
    "_id": { "$oid": "5c3b64fb547a852e6228325e" },
    "key": 164,
    "winCount": 272,
    "lossCount": 331,
    "banCount": 444,
    "magicDmg": { "$numberLong": "293792" },
    "physDmg": { "$numberLong": "6658719" },
    "trueDmg": { "$numberLong": "1510542" },
    "spell1Count": 0,
    "spell2Count": 0,
    "killCount": 3939,
    "deathCount": 4231,
    "assistCount": 4769,
    "gameTime": { "$numberLong": "940011" }
  },
  {
    "_id": { "$oid": "5c3b64fb547a852e6228325f" },
    "key": 201,
    "winCount": 163,
    "lossCount": 168,
    "banCount": 159,
    "magicDmg": { "$numberLong": "1736810" },
    "physDmg": { "$numberLong": "476278" },
    "trueDmg": { "$numberLong": "206344" },
    "spell1Count": 0,
    "spell2Count": 0,
    "killCount": 621,
    "deathCount": 1947,
    "assistCount": 4767,
    "gameTime": { "$numberLong": "545819" }
  },
  {
    "_id": { "$oid": "5c3b64fb547a852e62283260" },
    "key": 202,
    "winCount": 563,
    "lossCount": 564,
    "banCount": 238,
    "magicDmg": { "$numberLong": "1921332" },
    "physDmg": { "$numberLong": "20924424" },
    "trueDmg": { "$numberLong": "1099859" },
    "spell1Count": 0,
    "spell2Count": 0,
    "killCount": 8876,
    "deathCount": 6484,
    "assistCount": 10844,
    "gameTime": { "$numberLong": "1812379" }
  },
  {
    "_id": { "$oid": "5c3b64fb547a852e62283261" },
    "key": 203,
    "winCount": 158,
    "lossCount": 155,
    "banCount": 48,
    "magicDmg": { "$numberLong": "871986" },
    "physDmg": { "$numberLong": "4277052" },
    "trueDmg": { "$numberLong": "354719" },
    "spell1Count": 0,
    "spell2Count": 0,
    "killCount": 2294,
    "deathCount": 2103,
    "assistCount": 2624,
    "gameTime": { "$numberLong": "474994" }
  },
  {
    "_id": { "$oid": "5c3b64fb547a852e62283262" },
    "key": 222,
    "winCount": 510,
    "lossCount": 446,
    "banCount": 75,
    "magicDmg": { "$numberLong": "881152" },
    "physDmg": { "$numberLong": "17259831" },
    "trueDmg": { "$numberLong": "915956" },
    "spell1Count": 0,
    "spell2Count": 0,
    "killCount": 7383,
    "deathCount": 5753,
    "assistCount": 8547,
    "gameTime": { "$numberLong": "1482191" }
  },
  {
    "_id": { "$oid": "5c3b64fb547a852e62283263" },
    "key": 223,
    "winCount": 125,
    "lossCount": 138,
    "banCount": 58,
    "magicDmg": { "$numberLong": "2499362" },
    "physDmg": { "$numberLong": "625322" },
    "trueDmg": { "$numberLong": "172764" },
    "spell1Count": 0,
    "spell2Count": 0,
    "killCount": 1108,
    "deathCount": 1611,
    "assistCount": 2889,
    "gameTime": { "$numberLong": "418114" }
  },
  {
    "_id": { "$oid": "5c3b64fb547a852e62283264" },
    "key": 236,
    "winCount": 666,
    "lossCount": 685,
    "banCount": 976,
    "magicDmg": { "$numberLong": "3242478" },
    "physDmg": { "$numberLong": "23341308" },
    "trueDmg": { "$numberLong": "731496" },
    "spell1Count": 0,
    "spell2Count": 0,
    "killCount": 10295,
    "deathCount": 8011,
    "assistCount": 11034,
    "gameTime": { "$numberLong": "2213642" }
  },
  {
    "_id": { "$oid": "5c3b64fb547a852e62283265" },
    "key": 238,
    "winCount": 744,
    "lossCount": 765,
    "banCount": 2611,
    "magicDmg": { "$numberLong": "1270892" },
    "physDmg": { "$numberLong": "29950157" },
    "trueDmg": { "$numberLong": "1489897" },
    "spell1Count": 0,
    "spell2Count": 0,
    "killCount": 14173,
    "deathCount": 10620,
    "assistCount": 9897,
    "gameTime": { "$numberLong": "2479243" }
  },
  {
    "_id": { "$oid": "5c3b64fb547a852e62283266" },
    "key": 240,
    "winCount": 99,
    "lossCount": 92,
    "banCount": 63,
    "magicDmg": { "$numberLong": "32223" },
    "physDmg": { "$numberLong": "3294307" },
    "trueDmg": { "$numberLong": "406752" },
    "spell1Count": 0,
    "spell2Count": 0,
    "killCount": 1429,
    "deathCount": 1249,
    "assistCount": 1696,
    "gameTime": { "$numberLong": "309355" }
  },
  {
    "_id": { "$oid": "5c3b64fb547a852e62283267" },
    "key": 245,
    "winCount": 264,
    "lossCount": 233,
    "banCount": 163,
    "magicDmg": { "$numberLong": "8179979" },
    "physDmg": { "$numberLong": "1186360" },
    "trueDmg": { "$numberLong": "455982" },
    "spell1Count": 0,
    "spell2Count": 0,
    "killCount": 4096,
    "deathCount": 3229,
    "assistCount": 4030,
    "gameTime": { "$numberLong": "782674" }
  },
  {
    "_id": { "$oid": "5c3b64fb547a852e62283268" },
    "key": 254,
    "winCount": 174,
    "lossCount": 189,
    "banCount": 35,
    "magicDmg": { "$numberLong": "83671" },
    "physDmg": { "$numberLong": "5319463" },
    "trueDmg": { "$numberLong": "416018" },
    "spell1Count": 0,
    "spell2Count": 0,
    "killCount": 2624,
    "deathCount": 2548,
    "assistCount": 2952,
    "gameTime": { "$numberLong": "593100" }
  },
  {
    "_id": { "$oid": "5c3b64fb547a852e62283269" },
    "key": 266,
    "winCount": 431,
    "lossCount": 474,
    "banCount": 1160,
    "magicDmg": { "$numberLong": "90661" },
    "physDmg": { "$numberLong": "14279471" },
    "trueDmg": { "$numberLong": "669837" },
    "spell1Count": 0,
    "spell2Count": 0,
    "killCount": 5418,
    "deathCount": 5395,
    "assistCount": 6525,
    "gameTime": { "$numberLong": "1409042" }
  },
  {
    "_id": { "$oid": "5c3b64fb547a852e6228326a" },
    "key": 267,
    "winCount": 339,
    "lossCount": 300,
    "banCount": 42,
    "magicDmg": { "$numberLong": "5730130" },
    "physDmg": { "$numberLong": "697637" },
    "trueDmg": { "$numberLong": "423359" },
    "spell1Count": 0,
    "spell2Count": 0,
    "killCount": 1808,
    "deathCount": 3515,
    "assistCount": 11378,
    "gameTime": { "$numberLong": "974849" }
  },
  {
    "_id": { "$oid": "5c3b64fb547a852e6228326b" },
    "key": 268,
    "winCount": 145,
    "lossCount": 188,
    "banCount": 36,
    "magicDmg": { "$numberLong": "6062964" },
    "physDmg": { "$numberLong": "466351" },
    "trueDmg": { "$numberLong": "141115" },
    "spell1Count": 0,
    "spell2Count": 0,
    "killCount": 2147,
    "deathCount": 2766,
    "assistCount": 3825,
    "gameTime": { "$numberLong": "471925" }
  },
  {
    "_id": { "$oid": "5c3b64fb547a852e6228326c" },
    "key": 412,
    "winCount": 916,
    "lossCount": 1026,
    "banCount": 532,
    "magicDmg": { "$numberLong": "13171617" },
    "physDmg": { "$numberLong": "2997896" },
    "trueDmg": { "$numberLong": "1422236" },
    "spell1Count": 0,
    "spell2Count": 0,
    "killCount": 5827,
    "deathCount": 12256,
    "assistCount": 26361,
    "gameTime": { "$numberLong": "3152485" }
  },
  {
    "_id": { "$oid": "5c3b64fb547a852e6228326d" },
    "key": 420,
    "winCount": 296,
    "lossCount": 261,
    "banCount": 516,
    "magicDmg": { "$numberLong": "225472" },
    "physDmg": { "$numberLong": "11651343" },
    "trueDmg": { "$numberLong": "457136" },
    "spell1Count": 0,
    "spell2Count": 0,
    "killCount": 3546,
    "deathCount": 3838,
    "assistCount": 5018,
    "gameTime": { "$numberLong": "828547" }
  },
  {
    "_id": { "$oid": "5c3b64fb547a852e6228326e" },
    "key": 421,
    "winCount": 39,
    "lossCount": 59,
    "banCount": 12,
    "magicDmg": { "$numberLong": "82113" },
    "physDmg": { "$numberLong": "1211317" },
    "trueDmg": { "$numberLong": "184865" },
    "spell1Count": 0,
    "spell2Count": 0,
    "killCount": 667,
    "deathCount": 758,
    "assistCount": 989,
    "gameTime": { "$numberLong": "146832" }
  },
  {
    "_id": { "$oid": "5c3b64fb547a852e6228326f" },
    "key": 427,
    "winCount": 55,
    "lossCount": 50,
    "banCount": 32,
    "magicDmg": { "$numberLong": "600256" },
    "physDmg": { "$numberLong": "271493" },
    "trueDmg": { "$numberLong": "89298" },
    "spell1Count": 0,
    "spell2Count": 0,
    "killCount": 272,
    "deathCount": 550,
    "assistCount": 1682,
    "gameTime": { "$numberLong": "147270" }
  },
  {
    "_id": { "$oid": "5c3b64fb547a852e62283270" },
    "key": 429,
    "winCount": 160,
    "lossCount": 177,
    "banCount": 35,
    "magicDmg": { "$numberLong": "307178" },
    "physDmg": { "$numberLong": "5739142" },
    "trueDmg": { "$numberLong": "166858" },
    "spell1Count": 0,
    "spell2Count": 0,
    "killCount": 2778,
    "deathCount": 2350,
    "assistCount": 2948,
    "gameTime": { "$numberLong": "514694" }
  },
  {
    "_id": { "$oid": "5c3b64fb547a852e62283271" },
    "key": 432,
    "winCount": 203,
    "lossCount": 215,
    "banCount": 32,
    "magicDmg": { "$numberLong": "4668217" },
    "physDmg": { "$numberLong": "1084924" },
    "trueDmg": { "$numberLong": "368800" },
    "spell1Count": 0,
    "spell2Count": 0,
    "killCount": 2019,
    "deathCount": 2853,
    "assistCount": 6339,
    "gameTime": { "$numberLong": "623591" }
  },
  {
    "_id": { "$oid": "5c3b64fb547a852e62283272" },
    "key": 497,
    "winCount": 265,
    "lossCount": 260,
    "banCount": 60,
    "magicDmg": { "$numberLong": "3277047" },
    "physDmg": { "$numberLong": "715219" },
    "trueDmg": { "$numberLong": "404330" },
    "spell1Count": 0,
    "spell2Count": 0,
    "killCount": 1339,
    "deathCount": 3193,
    "assistCount": 8617,
    "gameTime": { "$numberLong": "800207" }
  },
  {
    "_id": { "$oid": "5c3b64fb547a852e62283273" },
    "key": 498,
    "winCount": 290,
    "lossCount": 309,
    "banCount": 51,
    "magicDmg": { "$numberLong": "487881" },
    "physDmg": { "$numberLong": "10549125" },
    "trueDmg": { "$numberLong": "437038" },
    "spell1Count": 0,
    "spell2Count": 0,
    "killCount": 4283,
    "deathCount": 3907,
    "assistCount": 6484,
    "gameTime": { "$numberLong": "865774" }
  },
  {
    "_id": { "$oid": "5c3b64fb547a852e62283274" },
    "key": 516,
    "winCount": 166,
    "lossCount": 186,
    "banCount": 70,
    "magicDmg": { "$numberLong": "3124176" },
    "physDmg": { "$numberLong": "2137101" },
    "trueDmg": { "$numberLong": "172760" },
    "spell1Count": 0,
    "spell2Count": 0,
    "killCount": 1548,
    "deathCount": 2244,
    "assistCount": 3788,
    "gameTime": { "$numberLong": "564408" }
  },
  {
    "_id": { "$oid": "5c3b64fb547a852e62283275" },
    "key": 518,
    "winCount": 662,
    "lossCount": 599,
    "banCount": 880,
    "magicDmg": { "$numberLong": "21645525" },
    "physDmg": { "$numberLong": "1699395" },
    "trueDmg": { "$numberLong": "961009" },
    "spell1Count": 0,
    "spell2Count": 0,
    "killCount": 7986,
    "deathCount": 8217,
    "assistCount": 12399,
    "gameTime": { "$numberLong": "1959767" }
  },
  {
    "_id": { "$oid": "5c3b64fb547a852e62283276" },
    "key": 555,
    "winCount": 682,
    "lossCount": 697,
    "banCount": 1858,
    "magicDmg": { "$numberLong": "270789" },
    "physDmg": { "$numberLong": "13881828" },
    "trueDmg": { "$numberLong": "3001385" },
    "spell1Count": 0,
    "spell2Count": 0,
    "killCount": 10612,
    "deathCount": 9101,
    "assistCount": 12278,
    "gameTime": { "$numberLong": "2226325" }
  }
]